python_markdown_oembed_extension/__init__.py
python_markdown_oembed_extension/endpoints.py
python_markdown_oembed_extension/inlinepatterns.py
python_markdown_oembed_extension/oembedextension.py
python_markdown_oembed_extension/tests/test_expectedHtml.html
python_markdown_oembed_extension/tests/test_markdown.md
python_markdown_oembed_extension/tests/test_markdown.py
python_markdown_oembed_extension/tests/vimeoMock.yaml
python_markdown_oembed_extension-0.3.1.dist-info/entry_points.txt
python_markdown_oembed_extension-0.3.1.dist-info/LICENSE
python_markdown_oembed_extension-0.3.1.dist-info/WHEEL
python_markdown_oembed_extension-0.3.1.dist-info/METADATA
python_markdown_oembed_extension-0.3.1.dist-info/RECORD
